pyjlib/__init__.py
pyjlib/_version.py
pyjlib/util/__init__.py
pyjlib/util/stringjoiner.py
tests/__init__.py
tests/util/__init__.py
tests/util/test_stringJoiner.py
pyjlib-0.0.1.dist-info/LICENSE
pyjlib-0.0.1.dist-info/METADATA
pyjlib-0.0.1.dist-info/WHEEL
pyjlib-0.0.1.dist-info/top_level.txt
pyjlib-0.0.1.dist-info/RECORD
