Metadata-Version: 2.1
Name: pyjlib
Version: 0.0.1
Summary: UNKNOWN
Home-page: https://github.com/maboualidev/PyJLib
Author: Mohammad Abouali
Author-email: maboualidev@gmail.com
License: UNKNOWN
Platform: UNKNOWN
Classifier: Programming Language :: Python :: 3
Classifier: Operating System :: OS Independent
Requires-Python: >=3.7
